taos/__init__.py
taos/bio.py
taos/cli.py
taos/config.py
taos/web.py
tests/taos/__init__.py
tests/taos/test_bio.py
taos-1.0.1.dist-info/LICENSE
taos-1.0.1.dist-info/METADATA
taos-1.0.1.dist-info/WHEEL
taos-1.0.1.dist-info/entry_points.txt
taos-1.0.1.dist-info/top_level.txt
taos-1.0.1.dist-info/RECORD
